ntt_fastapi-1.0.15.data/data/nttfastapi/source_code_assets/.env
ntt_fastapi-1.0.15.data/data/nttfastapi/source_code_assets/.example.env
ntt_fastapi-1.0.15.data/data/nttfastapi/source_code_assets/.gitignore
nttfastapi/__init__.py
nttfastapi/__main__.py
nttfastapi/cli.py
nttfastapi/constants.py
nttfastapi/source_code_assets/.gitignore
nttfastapi/source_code_assets/__init__.py
nttfastapi/source_code_assets/base.py
nttfastapi/source_code_assets/env.py
nttfastapi/source_code_assets/main.py
nttfastapi/source_code_assets/server.py
nttfastapi/source_code_assets/test.py
nttfastapi/source_code_assets/test_all.py
nttfastapi/source_code_assets/test_unittest.py
nttfastapi/utils/__init__.py
nttfastapi/utils/command_line.py
nttfastapi/utils/file_system.py
nttfastapi/utils/github_configuration.py
nttfastapi/utils/ntt_argparser.py
nttfastapi/utils/project_configuration.py
nttfastapi/utils/virtual_env.py
tests/__init__.py
tests/constants.py
tests/test_create_project_folder.py
tests/tools.py
tests/utils/__init__.py
tests/utils/test_command_line.py
tests/utils/test_file_system.py
tests/utils/test_github_configuration.py
tests/utils/test_ntt_argparser.py
tests/utils/test_project_configuration.py
tests/utils/test_virtual_env.py
ntt_fastapi-1.0.15.dist-info/LICENSE
ntt_fastapi-1.0.15.dist-info/METADATA
ntt_fastapi-1.0.15.dist-info/WHEEL
ntt_fastapi-1.0.15.dist-info/entry_points.txt
ntt_fastapi-1.0.15.dist-info/top_level.txt
ntt_fastapi-1.0.15.dist-info/RECORD
