Metadata-Version: 2.1
Name: ntt-fastapi
Version: 1.0.15
Summary: The Framework which helps developers work with FastAPI easier
Home-page: https://github.com/threezinedine/ntt-fastapi
Author: threezinedine
Author-email: threezinedine@email.com
License: UNKNOWN
Platform: UNKNOWN
Classifier: Intended Audience :: Developers
Classifier: License :: OSI Approved :: MIT License
Classifier: Programming Language :: Python
Classifier: Programming Language :: Python :: 3
Classifier: Programming Language :: Python :: 3.6
Classifier: Programming Language :: Python :: 3.7
Classifier: Programming Language :: Python :: 3.8
Classifier: Programming Language :: Python :: 3.9
Requires-Python: >=3.6
License-File: LICENSE
